kitten/__init__.py
kitten-0.6.2.dist-info/LICENSE
kitten-0.6.2.dist-info/METADATA
kitten-0.6.2.dist-info/WHEEL
kitten-0.6.2.dist-info/entry_points.txt
kitten-0.6.2.dist-info/top_level.txt
kitten-0.6.2.dist-info/RECORD
