Metadata-Version: 2.1
Name: kitten
Version: 0.6.2
Summary: Tiny multi-server automation tool.
Home-page: https://github.com/hoffa/kitten
Author: Chris Rehn
Author-email: chris@rehn.me
License: MIT
Platform: UNKNOWN
Classifier: Development Status :: 5 - Production/Stable
Classifier: Environment :: Console
Classifier: License :: OSI Approved :: MIT License
Classifier: Operating System :: OS Independent
Classifier: Programming Language :: Python :: 3
Classifier: Programming Language :: Python :: 3.6
Classifier: Programming Language :: Python :: 3.7
Classifier: Topic :: System :: Monitoring
Classifier: Topic :: System :: Systems Administration
Classifier: Topic :: Utilities
Requires-Python: >=3.6
License-File: LICENSE
Requires-Dist: boto3
Requires-Dist: fabric (>=2.4)
